{
  "generated_at": "2026-07-22T18:04:48.049746+07:00",
  "state_schema_version": "v10.4-finite-two-pass-queue",
  "dispatch_next": true,
  "pending_count": 4,
  "pending_room_count": 9,
  "completed_count": 6,
  "coverage_complete_count": 10,
  "total_match_count": 14,
  "total_stream_count": 9,
  "progress_count": 5,
  "new_link_count": 5,
  "refreshed_link_count": 0,
  "queue_progress_count": 58,
  "terminal_progress_count": 44,
  "newly_attempted_count": 14,
  "queue_total_rooms": 53,
  "queue_success_rooms": 16,
  "queue_exhausted_rooms": 28,
  "queue_terminal_rooms": 44,
  "queue_attempts_total": 81,
  "chain_runs": 1,
  "no_progress_runs": 0,
  "no_queue_progress_runs": 0,
  "unchanged_pending_runs": 0,
  "rate_limit_only_runs": 0,
  "rate_limit_only_run": false,
  "pending_fingerprint": "36b9cf9121615c707392da3d963330b4b182a25682ab3a2cfbf9de347cfd404c",
  "stop_reason": "",
  "rate_limited": false,
  "rate_limit_url": "",
  "global_room_budget": 48,
  "global_room_budget_used": 14,
  "count": 4,
  "matches": [
    {
      "base_url": "https://socolivep.cv/truc-tiep/university-azzurri-fc-vs-macarthur-fc-22-07-2026-1700/",
      "match_name": "University Azzurri FC vs Macarthur FC",
      "scheduled_at": "2026-07-22T17:00:00+07:00",
      "rooms": [
        {
          "url": "https://socolivep.cv/truc-tiep/university-azzurri-fc-vs-macarthur-fc-22-07-2026-1700?blv=603255",
          "blv": "LION",
          "blv_id": "603255"
        },
        {
          "url": "https://socolivep.cv/truc-tiep/university-azzurri-fc-vs-macarthur-fc-22-07-2026-1700?blv=557845",
          "blv": "A TÚ",
          "blv_id": "557845"
        },
        {
          "url": "https://socolivep.cv/truc-tiep/university-azzurri-fc-vs-macarthur-fc-22-07-2026-1700",
          "blv": "XEM NGAY",
          "blv_id": ""
        }
      ],
      "streams": [],
      "coverage": {
        "found_streams": 0,
        "found_blv_ids": [],
        "goal": 4,
        "source_goal_reached": false,
        "room_queue_complete": false,
        "complete": false,
        "max_streams_per_blv": 2,
        "total_explicit_blv_rooms": 2,
        "pending_room_keys": [
          "557845"
        ],
        "room_progress": {
          "603255": {
            "key": "603255",
            "url": "https://socolivep.cv/truc-tiep/university-azzurri-fc-vs-macarthur-fc-22-07-2026-1700?blv=603255",
            "blv": "LION",
            "blv_id": "603255",
            "status": "exhausted",
            "attempts": 2,
            "attempts_total": 2,
            "ever_attempted": true,
            "valid_stream_ever_found": false,
            "needs_token_refresh": true,
            "completion_reason": "no_valid_stream_after_max_attempts",
            "rate_limit_hits": 0,
            "last_http_status": 200,
            "last_stream_count": 0,
            "last_error": "Token cũ đã hết hạn; giữ nguyên attempts_total và trạng thái hoàn tất của BLV."
          },
          "304148": {
            "key": "304148",
            "url": "https://socolivep.cv/truc-tiep/university-azzurri-fc-vs-macarthur-fc-22-07-2026-1700?blv=304148",
            "blv": "LUCAS",
            "blv_id": "304148",
            "status": "exhausted",
            "attempts": 2,
            "attempts_total": 2,
            "ever_attempted": true,
            "valid_stream_ever_found": false,
            "needs_token_refresh": true,
            "completion_reason": "no_valid_stream_after_max_attempts",
            "rate_limit_hits": 0,
            "last_http_status": 200,
            "last_stream_count": 0,
            "last_error": "Token cũ đã hết hạn; giữ nguyên attempts_total và trạng thái hoàn tất của BLV."
          },
          "__base__": {
            "key": "__base__",
            "url": "https://socolivep.cv/truc-tiep/university-azzurri-fc-vs-macarthur-fc-22-07-2026-1700",
            "blv": "XEM NGAY",
            "blv_id": "",
            "status": "pending",
            "attempts": 0,
            "attempts_total": 0,
            "ever_attempted": false,
            "valid_stream_ever_found": false,
            "needs_token_refresh": false,
            "completion_reason": "",
            "rate_limit_hits": 0,
            "last_http_status": null,
            "last_stream_count": 0,
            "last_error": ""
          },
          "557845": {
            "key": "557845",
            "url": "https://socolivep.cv/truc-tiep/university-azzurri-fc-vs-macarthur-fc-22-07-2026-1700?blv=557845",
            "blv": "A TÚ",
            "blv_id": "557845",
            "status": "retry",
            "attempts": 1,
            "attempts_total": 1,
            "ever_attempted": true,
            "valid_stream_ever_found": false,
            "needs_token_refresh": true,
            "completion_reason": "",
            "rate_limit_hits": 0,
            "last_http_status": 200,
            "last_stream_count": 0,
            "last_error": "Token cũ đã hết hạn; giữ nguyên attempts_total và trạng thái hoàn tất của BLV."
          }
        }
      },
      "attempted_room_ids": [
        "304148",
        "557845",
        "603255"
      ],
      "room_progress": {
        "603255": {
          "key": "603255",
          "url": "https://socolivep.cv/truc-tiep/university-azzurri-fc-vs-macarthur-fc-22-07-2026-1700?blv=603255",
          "blv": "LION",
          "blv_id": "603255",
          "status": "exhausted",
          "attempts": 2,
          "attempts_total": 2,
          "ever_attempted": true,
          "valid_stream_ever_found": false,
          "needs_token_refresh": true,
          "completion_reason": "no_valid_stream_after_max_attempts",
          "rate_limit_hits": 0,
          "last_http_status": 200,
          "last_stream_count": 0,
          "last_error": "Token cũ đã hết hạn; giữ nguyên attempts_total và trạng thái hoàn tất của BLV."
        },
        "304148": {
          "key": "304148",
          "url": "https://socolivep.cv/truc-tiep/university-azzurri-fc-vs-macarthur-fc-22-07-2026-1700?blv=304148",
          "blv": "LUCAS",
          "blv_id": "304148",
          "status": "exhausted",
          "attempts": 2,
          "attempts_total": 2,
          "ever_attempted": true,
          "valid_stream_ever_found": false,
          "needs_token_refresh": true,
          "completion_reason": "no_valid_stream_after_max_attempts",
          "rate_limit_hits": 0,
          "last_http_status": 200,
          "last_stream_count": 0,
          "last_error": "Token cũ đã hết hạn; giữ nguyên attempts_total và trạng thái hoàn tất của BLV."
        },
        "__base__": {
          "key": "__base__",
          "url": "https://socolivep.cv/truc-tiep/university-azzurri-fc-vs-macarthur-fc-22-07-2026-1700",
          "blv": "XEM NGAY",
          "blv_id": "",
          "status": "pending",
          "attempts": 0,
          "attempts_total": 0,
          "ever_attempted": false,
          "valid_stream_ever_found": false,
          "needs_token_refresh": false,
          "completion_reason": "",
          "rate_limit_hits": 0,
          "last_http_status": null,
          "last_stream_count": 0,
          "last_error": ""
        },
        "557845": {
          "key": "557845",
          "url": "https://socolivep.cv/truc-tiep/university-azzurri-fc-vs-macarthur-fc-22-07-2026-1700?blv=557845",
          "blv": "A TÚ",
          "blv_id": "557845",
          "status": "retry",
          "attempts": 1,
          "attempts_total": 1,
          "ever_attempted": true,
          "valid_stream_ever_found": false,
          "needs_token_refresh": true,
          "completion_reason": "",
          "rate_limit_hits": 0,
          "last_http_status": 200,
          "last_stream_count": 0,
          "last_error": "Token cũ đã hết hạn; giữ nguyên attempts_total và trạng thái hoàn tất của BLV."
        }
      },
      "pending_room_keys": [
        "557845"
      ]
    },
    {
      "base_url": "https://socolivep.cv/truc-tiep/laos-women-vs-indonesia-women-22-07-2026-1945/",
      "match_name": "Laos Women vs Indonesia Women",
      "scheduled_at": "2026-07-22T19:45:00+07:00",
      "rooms": [
        {
          "url": "https://socolivep.cv/truc-tiep/laos-women-vs-indonesia-women-22-07-2026-1945?blv=400722",
          "blv": "TUẤN CÙI",
          "blv_id": "400722"
        },
        {
          "url": "https://socolivep.cv/truc-tiep/laos-women-vs-indonesia-women-22-07-2026-1945?blv=406865",
          "blv": "ANH TÀI",
          "blv_id": "406865"
        },
        {
          "url": "https://socolivep.cv/truc-tiep/laos-women-vs-indonesia-women-22-07-2026-1945?blv=617313",
          "blv": "VINFAST",
          "blv_id": "617313"
        },
        {
          "url": "https://socolivep.cv/truc-tiep/laos-women-vs-indonesia-women-22-07-2026-1945?blv=597929",
          "blv": "CÁO",
          "blv_id": "597929"
        },
        {
          "url": "https://socolivep.cv/truc-tiep/laos-women-vs-indonesia-women-22-07-2026-1945",
          "blv": "XEM NGAY",
          "blv_id": ""
        }
      ],
      "streams": [],
      "coverage": {
        "found_streams": 0,
        "found_blv_ids": [],
        "goal": 8,
        "source_goal_reached": false,
        "room_queue_complete": false,
        "complete": false,
        "max_streams_per_blv": 2,
        "total_explicit_blv_rooms": 4,
        "pending_room_keys": [
          "400722",
          "406865",
          "617313",
          "597929"
        ],
        "room_progress": {
          "400722": {
            "key": "400722",
            "url": "https://socolivep.cv/truc-tiep/laos-women-vs-indonesia-women-22-07-2026-1945?blv=400722",
            "blv": "TUẤN CÙI",
            "blv_id": "400722",
            "status": "retry",
            "attempts": 1,
            "attempts_total": 1,
            "ever_attempted": true,
            "valid_stream_ever_found": false,
            "needs_token_refresh": true,
            "completion_reason": "",
            "rate_limit_hits": 0,
            "last_http_status": 200,
            "last_stream_count": 0,
            "last_error": "Token cũ đã hết hạn; giữ nguyên attempts_total và trạng thái hoàn tất của BLV."
          },
          "406865": {
            "key": "406865",
            "url": "https://socolivep.cv/truc-tiep/laos-women-vs-indonesia-women-22-07-2026-1945?blv=406865",
            "blv": "ANH TÀI",
            "blv_id": "406865",
            "status": "retry",
            "attempts": 1,
            "attempts_total": 1,
            "ever_attempted": true,
            "valid_stream_ever_found": false,
            "needs_token_refresh": true,
            "completion_reason": "",
            "rate_limit_hits": 0,
            "last_http_status": 200,
            "last_stream_count": 0,
            "last_error": "Token cũ đã hết hạn; giữ nguyên attempts_total và trạng thái hoàn tất của BLV."
          },
          "617313": {
            "key": "617313",
            "url": "https://socolivep.cv/truc-tiep/laos-women-vs-indonesia-women-22-07-2026-1945?blv=617313",
            "blv": "VINFAST",
            "blv_id": "617313",
            "status": "retry",
            "attempts": 1,
            "attempts_total": 1,
            "ever_attempted": true,
            "valid_stream_ever_found": false,
            "needs_token_refresh": true,
            "completion_reason": "",
            "rate_limit_hits": 0,
            "last_http_status": 200,
            "last_stream_count": 0,
            "last_error": "Token cũ đã hết hạn; giữ nguyên attempts_total và trạng thái hoàn tất của BLV."
          },
          "597929": {
            "key": "597929",
            "url": "https://socolivep.cv/truc-tiep/laos-women-vs-indonesia-women-22-07-2026-1945?blv=597929",
            "blv": "CÁO",
            "blv_id": "597929",
            "status": "retry",
            "attempts": 1,
            "attempts_total": 1,
            "ever_attempted": true,
            "valid_stream_ever_found": false,
            "needs_token_refresh": true,
            "completion_reason": "",
            "rate_limit_hits": 0,
            "last_http_status": 200,
            "last_stream_count": 0,
            "last_error": "Token cũ đã hết hạn; giữ nguyên attempts_total và trạng thái hoàn tất của BLV."
          },
          "__base__": {
            "key": "__base__",
            "url": "https://socolivep.cv/truc-tiep/laos-women-vs-indonesia-women-22-07-2026-1945",
            "blv": "XEM NGAY",
            "blv_id": "",
            "status": "pending",
            "attempts": 0,
            "attempts_total": 0,
            "ever_attempted": false,
            "valid_stream_ever_found": false,
            "needs_token_refresh": false,
            "completion_reason": "",
            "rate_limit_hits": 0,
            "last_http_status": null,
            "last_stream_count": 0,
            "last_error": ""
          }
        }
      },
      "attempted_room_ids": [
        "400722",
        "406865",
        "597929",
        "617313"
      ],
      "room_progress": {
        "400722": {
          "key": "400722",
          "url": "https://socolivep.cv/truc-tiep/laos-women-vs-indonesia-women-22-07-2026-1945?blv=400722",
          "blv": "TUẤN CÙI",
          "blv_id": "400722",
          "status": "retry",
          "attempts": 1,
          "attempts_total": 1,
          "ever_attempted": true,
          "valid_stream_ever_found": false,
          "needs_token_refresh": true,
          "completion_reason": "",
          "rate_limit_hits": 0,
          "last_http_status": 200,
          "last_stream_count": 0,
          "last_error": "Token cũ đã hết hạn; giữ nguyên attempts_total và trạng thái hoàn tất của BLV."
        },
        "406865": {
          "key": "406865",
          "url": "https://socolivep.cv/truc-tiep/laos-women-vs-indonesia-women-22-07-2026-1945?blv=406865",
          "blv": "ANH TÀI",
          "blv_id": "406865",
          "status": "retry",
          "attempts": 1,
          "attempts_total": 1,
          "ever_attempted": true,
          "valid_stream_ever_found": false,
          "needs_token_refresh": true,
          "completion_reason": "",
          "rate_limit_hits": 0,
          "last_http_status": 200,
          "last_stream_count": 0,
          "last_error": "Token cũ đã hết hạn; giữ nguyên attempts_total và trạng thái hoàn tất của BLV."
        },
        "617313": {
          "key": "617313",
          "url": "https://socolivep.cv/truc-tiep/laos-women-vs-indonesia-women-22-07-2026-1945?blv=617313",
          "blv": "VINFAST",
          "blv_id": "617313",
          "status": "retry",
          "attempts": 1,
          "attempts_total": 1,
          "ever_attempted": true,
          "valid_stream_ever_found": false,
          "needs_token_refresh": true,
          "completion_reason": "",
          "rate_limit_hits": 0,
          "last_http_status": 200,
          "last_stream_count": 0,
          "last_error": "Token cũ đã hết hạn; giữ nguyên attempts_total và trạng thái hoàn tất của BLV."
        },
        "597929": {
          "key": "597929",
          "url": "https://socolivep.cv/truc-tiep/laos-women-vs-indonesia-women-22-07-2026-1945?blv=597929",
          "blv": "CÁO",
          "blv_id": "597929",
          "status": "retry",
          "attempts": 1,
          "attempts_total": 1,
          "ever_attempted": true,
          "valid_stream_ever_found": false,
          "needs_token_refresh": true,
          "completion_reason": "",
          "rate_limit_hits": 0,
          "last_http_status": 200,
          "last_stream_count": 0,
          "last_error": "Token cũ đã hết hạn; giữ nguyên attempts_total và trạng thái hoàn tất của BLV."
        },
        "__base__": {
          "key": "__base__",
          "url": "https://socolivep.cv/truc-tiep/laos-women-vs-indonesia-women-22-07-2026-1945",
          "blv": "XEM NGAY",
          "blv_id": "",
          "status": "pending",
          "attempts": 0,
          "attempts_total": 0,
          "ever_attempted": false,
          "valid_stream_ever_found": false,
          "needs_token_refresh": false,
          "completion_reason": "",
          "rate_limit_hits": 0,
          "last_http_status": null,
          "last_stream_count": 0,
          "last_error": ""
        }
      },
      "pending_room_keys": [
        "400722",
        "406865",
        "617313",
        "597929"
      ]
    },
    {
      "base_url": "https://socolivep.cv/truc-tiep/fk-kokand-1912-vs-fc-okmk-olmaliq-22-07-2026-2200/",
      "match_name": "FK Kokand 1912 vs FC OKMK Olmaliq",
      "scheduled_at": "2026-07-22T22:00:00+07:00",
      "rooms": [
        {
          "url": "https://socolivep.cv/truc-tiep/fk-kokand-1912-vs-fc-okmk-olmaliq-22-07-2026-2200?blv=387694",
          "blv": "CR Bưởi",
          "blv_id": "387694"
        },
        {
          "url": "https://socolivep.cv/truc-tiep/fk-kokand-1912-vs-fc-okmk-olmaliq-22-07-2026-2200?blv=250874",
          "blv": "FIREMAN",
          "blv_id": "250874"
        },
        {
          "url": "https://socolivep.cv/truc-tiep/fk-kokand-1912-vs-fc-okmk-olmaliq-22-07-2026-2200?blv=132343",
          "blv": "LONG",
          "blv_id": "132343"
        },
        {
          "url": "https://socolivep.cv/truc-tiep/fk-kokand-1912-vs-fc-okmk-olmaliq-22-07-2026-2200",
          "blv": "XEM NGAY",
          "blv_id": ""
        }
      ],
      "streams": [
        {
          "url": "https://pull.niur.live/live/stream-387694_lhd.m3u8?txSecret=4a63adaf93bddcfc793b72c2eeef84f9&txTime=6a60a551",
          "queue_room_key": "387694",
          "room_url": "https://socolivep.cv/truc-tiep/fk-kokand-1912-vs-fc-okmk-olmaliq-22-07-2026-2200?blv=387694",
          "blv": "CR Bưởi",
          "blv_id": "387694",
          "source_id": "387694",
          "source_provenance": [
            "final-no-stream-scan",
            "harvest-final"
          ],
          "source_confidence": "embedded",
          "mapping_mode": "exact-room-id",
          "discovered_from_room_url": "https://socolivep.cv/truc-tiep/fk-kokand-1912-vs-fc-okmk-olmaliq-22-07-2026-2200?blv=387694",
          "discovered_from_blv": "CR Bưởi",
          "discovered_at": "2026-07-22T18:02:37.721870+07:00",
          "valid_until": "2026-07-22T18:11:13+07:00",
          "is_expired": false
        }
      ],
      "coverage": {
        "found_streams": 1,
        "found_blv_ids": [
          "387694"
        ],
        "goal": 6,
        "source_goal_reached": false,
        "room_queue_complete": false,
        "complete": false,
        "max_streams_per_blv": 2,
        "total_explicit_blv_rooms": 3,
        "pending_room_keys": [
          "250874",
          "132343"
        ],
        "room_progress": {
          "387694": {
            "key": "387694",
            "url": "https://socolivep.cv/truc-tiep/fk-kokand-1912-vs-fc-okmk-olmaliq-22-07-2026-2200?blv=387694",
            "blv": "CR Bưởi",
            "blv_id": "387694",
            "status": "success",
            "attempts": 1,
            "attempts_total": 1,
            "ever_attempted": true,
            "valid_stream_ever_found": true,
            "needs_token_refresh": false,
            "completion_reason": "valid_stream",
            "rate_limit_hits": 0,
            "last_http_status": 200,
            "last_stream_count": 1,
            "last_error": "console/error: Failed to load resource: net::ERR_FAILED; console/error: Failed to load resource: net::ERR_FAILED; console/error: Failed to load resource: net::ERR_FAILED"
          },
          "250874": {
            "key": "250874",
            "url": "https://socolivep.cv/truc-tiep/fk-kokand-1912-vs-fc-okmk-olmaliq-22-07-2026-2200?blv=250874",
            "blv": "FIREMAN",
            "blv_id": "250874",
            "status": "retry",
            "attempts": 1,
            "attempts_total": 1,
            "ever_attempted": true,
            "valid_stream_ever_found": false,
            "needs_token_refresh": true,
            "completion_reason": "",
            "rate_limit_hits": 0,
            "last_http_status": 200,
            "last_stream_count": 0,
            "last_error": "Token cũ đã hết hạn; giữ nguyên attempts_total và trạng thái hoàn tất của BLV."
          },
          "132343": {
            "key": "132343",
            "url": "https://socolivep.cv/truc-tiep/fk-kokand-1912-vs-fc-okmk-olmaliq-22-07-2026-2200?blv=132343",
            "blv": "LONG",
            "blv_id": "132343",
            "status": "retry",
            "attempts": 1,
            "attempts_total": 1,
            "ever_attempted": true,
            "valid_stream_ever_found": false,
            "needs_token_refresh": true,
            "completion_reason": "",
            "rate_limit_hits": 0,
            "last_http_status": 200,
            "last_stream_count": 0,
            "last_error": "Token cũ đã hết hạn; giữ nguyên attempts_total và trạng thái hoàn tất của BLV."
          },
          "__base__": {
            "key": "__base__",
            "url": "https://socolivep.cv/truc-tiep/fk-kokand-1912-vs-fc-okmk-olmaliq-22-07-2026-2200",
            "blv": "XEM NGAY",
            "blv_id": "",
            "status": "pending",
            "attempts": 0,
            "attempts_total": 0,
            "ever_attempted": false,
            "valid_stream_ever_found": false,
            "needs_token_refresh": false,
            "completion_reason": "",
            "rate_limit_hits": 0,
            "last_http_status": null,
            "last_stream_count": 0,
            "last_error": ""
          }
        }
      },
      "attempted_room_ids": [
        "132343",
        "250874",
        "387694"
      ],
      "room_progress": {
        "387694": {
          "key": "387694",
          "url": "https://socolivep.cv/truc-tiep/fk-kokand-1912-vs-fc-okmk-olmaliq-22-07-2026-2200?blv=387694",
          "blv": "CR Bưởi",
          "blv_id": "387694",
          "status": "success",
          "attempts": 1,
          "attempts_total": 1,
          "ever_attempted": true,
          "valid_stream_ever_found": true,
          "needs_token_refresh": false,
          "completion_reason": "valid_stream",
          "rate_limit_hits": 0,
          "last_http_status": 200,
          "last_stream_count": 1,
          "last_error": "console/error: Failed to load resource: net::ERR_FAILED; console/error: Failed to load resource: net::ERR_FAILED; console/error: Failed to load resource: net::ERR_FAILED"
        },
        "250874": {
          "key": "250874",
          "url": "https://socolivep.cv/truc-tiep/fk-kokand-1912-vs-fc-okmk-olmaliq-22-07-2026-2200?blv=250874",
          "blv": "FIREMAN",
          "blv_id": "250874",
          "status": "retry",
          "attempts": 1,
          "attempts_total": 1,
          "ever_attempted": true,
          "valid_stream_ever_found": false,
          "needs_token_refresh": true,
          "completion_reason": "",
          "rate_limit_hits": 0,
          "last_http_status": 200,
          "last_stream_count": 0,
          "last_error": "Token cũ đã hết hạn; giữ nguyên attempts_total và trạng thái hoàn tất của BLV."
        },
        "132343": {
          "key": "132343",
          "url": "https://socolivep.cv/truc-tiep/fk-kokand-1912-vs-fc-okmk-olmaliq-22-07-2026-2200?blv=132343",
          "blv": "LONG",
          "blv_id": "132343",
          "status": "retry",
          "attempts": 1,
          "attempts_total": 1,
          "ever_attempted": true,
          "valid_stream_ever_found": false,
          "needs_token_refresh": true,
          "completion_reason": "",
          "rate_limit_hits": 0,
          "last_http_status": 200,
          "last_stream_count": 0,
          "last_error": "Token cũ đã hết hạn; giữ nguyên attempts_total và trạng thái hoàn tất của BLV."
        },
        "__base__": {
          "key": "__base__",
          "url": "https://socolivep.cv/truc-tiep/fk-kokand-1912-vs-fc-okmk-olmaliq-22-07-2026-2200",
          "blv": "XEM NGAY",
          "blv_id": "",
          "status": "pending",
          "attempts": 0,
          "attempts_total": 0,
          "ever_attempted": false,
          "valid_stream_ever_found": false,
          "needs_token_refresh": false,
          "completion_reason": "",
          "rate_limit_hits": 0,
          "last_http_status": null,
          "last_stream_count": 0,
          "last_error": ""
        }
      },
      "pending_room_keys": [
        "250874",
        "132343"
      ]
    },
    {
      "base_url": "https://socolivep.cv/truc-tiep/tottenham-hotspur-vs-milton-keynes-dons-22-07-2026-2200/",
      "match_name": "Tottenham Hotspur vs Milton Keynes Dons",
      "scheduled_at": "2026-07-22T22:00:00+07:00",
      "rooms": [
        {
          "url": "https://socolivep.cv/truc-tiep/tottenham-hotspur-vs-milton-keynes-dons-22-07-2026-2200?blv=168740",
          "blv": "ZIDANE",
          "blv_id": "168740"
        },
        {
          "url": "https://socolivep.cv/truc-tiep/tottenham-hotspur-vs-milton-keynes-dons-22-07-2026-2200?blv=557845",
          "blv": "A TÚ",
          "blv_id": "557845"
        },
        {
          "url": "https://socolivep.cv/truc-tiep/tottenham-hotspur-vs-milton-keynes-dons-22-07-2026-2200?blv=459401",
          "blv": "BÉO",
          "blv_id": "459401"
        },
        {
          "url": "https://socolivep.cv/truc-tiep/tottenham-hotspur-vs-milton-keynes-dons-22-07-2026-2200?blv=612098",
          "blv": "BEN 10",
          "blv_id": "612098"
        },
        {
          "url": "https://socolivep.cv/truc-tiep/tottenham-hotspur-vs-milton-keynes-dons-22-07-2026-2200?blv=598119",
          "blv": "A TINH",
          "blv_id": "598119"
        },
        {
          "url": "https://socolivep.cv/truc-tiep/tottenham-hotspur-vs-milton-keynes-dons-22-07-2026-2200?blv=552832",
          "blv": "LOGAN",
          "blv_id": "552832"
        },
        {
          "url": "https://socolivep.cv/truc-tiep/tottenham-hotspur-vs-milton-keynes-dons-22-07-2026-2200",
          "blv": "XEM NGAY",
          "blv_id": ""
        }
      ],
      "streams": [
        {
          "url": "https://pull.niues.live/live/stream-557845_lhd.m3u8?auth_key=1784721715-0-0-9d13c77988b7abc2697f9dc1fe425a4e",
          "queue_room_key": "557845",
          "room_url": "https://socolivep.cv/truc-tiep/tottenham-hotspur-vs-milton-keynes-dons-22-07-2026-2200?blv=557845",
          "blv": "A TÚ",
          "blv_id": "557845",
          "source_id": "557845",
          "source_provenance": [
            "final-no-stream-scan",
            "harvest-final"
          ],
          "source_confidence": "embedded",
          "mapping_mode": "exact-room-id",
          "discovered_from_room_url": "https://socolivep.cv/truc-tiep/tottenham-hotspur-vs-milton-keynes-dons-22-07-2026-2200?blv=557845",
          "discovered_from_blv": "A TÚ",
          "discovered_at": "2026-07-22T18:03:41.737308+07:00",
          "valid_until": "2026-07-22T19:01:55+07:00",
          "is_expired": false
        },
        {
          "url": "https://pull.niur.live/live/stream-459401_lhd.m3u8?txSecret=d2c80f73ba2dabfc16a59725f4e3cd75&txTime=6a60f4ef",
          "queue_room_key": "459401",
          "room_url": "https://socolivep.cv/truc-tiep/tottenham-hotspur-vs-milton-keynes-dons-22-07-2026-2200?blv=459401",
          "blv": "BÉO",
          "blv_id": "459401",
          "source_id": "459401",
          "source_provenance": [
            "final-no-stream-scan",
            "harvest-final"
          ],
          "source_confidence": "embedded",
          "mapping_mode": "exact-room-id",
          "discovered_from_room_url": "https://socolivep.cv/truc-tiep/tottenham-hotspur-vs-milton-keynes-dons-22-07-2026-2200?blv=459401",
          "discovered_from_blv": "BÉO",
          "discovered_at": "2026-07-22T18:03:57.825459+07:00",
          "valid_until": "2026-07-22T23:50:55+07:00",
          "is_expired": false
        },
        {
          "url": "https://pull.niues.live/live/stream-612098_lhd.m3u8?auth_key=1784721235-0-0-b5c2ed0f325cfbfc1243b3b805c1a232",
          "queue_room_key": "612098",
          "room_url": "https://socolivep.cv/truc-tiep/tottenham-hotspur-vs-milton-keynes-dons-22-07-2026-2200?blv=612098",
          "blv": "BEN 10",
          "blv_id": "612098",
          "source_id": "612098",
          "source_provenance": [
            "final-no-stream-scan",
            "harvest-final"
          ],
          "source_confidence": "embedded",
          "mapping_mode": "exact-room-id",
          "discovered_from_room_url": "https://socolivep.cv/truc-tiep/tottenham-hotspur-vs-milton-keynes-dons-22-07-2026-2200?blv=612098",
          "discovered_from_blv": "BEN 10",
          "discovered_at": "2026-07-22T18:04:13.879293+07:00",
          "valid_until": "2026-07-22T18:53:55+07:00",
          "is_expired": false
        },
        {
          "url": "https://pull.niues.live/live/stream-552832_lhd.m3u8?auth_key=1784721055-0-0-6b690b9baf42a97573cb413444111b11",
          "queue_room_key": "552832",
          "room_url": "https://socolivep.cv/truc-tiep/tottenham-hotspur-vs-milton-keynes-dons-22-07-2026-2200?blv=552832",
          "blv": "LOGAN",
          "blv_id": "552832",
          "source_id": "552832",
          "source_provenance": [
            "final-no-stream-scan",
            "harvest-final"
          ],
          "source_confidence": "embedded",
          "mapping_mode": "exact-room-id",
          "discovered_from_room_url": "https://socolivep.cv/truc-tiep/tottenham-hotspur-vs-milton-keynes-dons-22-07-2026-2200?blv=552832",
          "discovered_from_blv": "LOGAN",
          "discovered_at": "2026-07-22T18:04:46.019886+07:00",
          "valid_until": "2026-07-22T18:50:55+07:00",
          "is_expired": false
        }
      ],
      "coverage": {
        "found_streams": 4,
        "found_blv_ids": [
          "459401",
          "552832",
          "557845",
          "612098"
        ],
        "goal": 12,
        "source_goal_reached": false,
        "room_queue_complete": false,
        "complete": false,
        "max_streams_per_blv": 2,
        "total_explicit_blv_rooms": 6,
        "pending_room_keys": [
          "168740",
          "598119"
        ],
        "room_progress": {
          "168740": {
            "key": "168740",
            "url": "https://socolivep.cv/truc-tiep/tottenham-hotspur-vs-milton-keynes-dons-22-07-2026-2200?blv=168740",
            "blv": "ZIDANE",
            "blv_id": "168740",
            "status": "retry",
            "attempts": 1,
            "attempts_total": 1,
            "ever_attempted": true,
            "valid_stream_ever_found": false,
            "needs_token_refresh": true,
            "completion_reason": "",
            "rate_limit_hits": 0,
            "last_http_status": 200,
            "last_stream_count": 0,
            "last_error": "Token cũ đã hết hạn; giữ nguyên attempts_total và trạng thái hoàn tất của BLV."
          },
          "557845": {
            "key": "557845",
            "url": "https://socolivep.cv/truc-tiep/tottenham-hotspur-vs-milton-keynes-dons-22-07-2026-2200?blv=557845",
            "blv": "A TÚ",
            "blv_id": "557845",
            "status": "success",
            "attempts": 1,
            "attempts_total": 1,
            "ever_attempted": true,
            "valid_stream_ever_found": true,
            "needs_token_refresh": false,
            "completion_reason": "valid_stream",
            "rate_limit_hits": 0,
            "last_http_status": 200,
            "last_stream_count": 1,
            "last_error": "console/error: Failed to load resource: net::ERR_FAILED; console/error: Failed to load resource: net::ERR_FAILED; console/error: Failed to load resource: net::ERR_FAILED"
          },
          "459401": {
            "key": "459401",
            "url": "https://socolivep.cv/truc-tiep/tottenham-hotspur-vs-milton-keynes-dons-22-07-2026-2200?blv=459401",
            "blv": "BÉO",
            "blv_id": "459401",
            "status": "success",
            "attempts": 1,
            "attempts_total": 1,
            "ever_attempted": true,
            "valid_stream_ever_found": true,
            "needs_token_refresh": false,
            "completion_reason": "valid_stream",
            "rate_limit_hits": 0,
            "last_http_status": 200,
            "last_stream_count": 1,
            "last_error": "console/error: Failed to load resource: net::ERR_FAILED; console/error: Failed to load resource: net::ERR_FAILED; console/error: Failed to load resource: net::ERR_FAILED"
          },
          "612098": {
            "key": "612098",
            "url": "https://socolivep.cv/truc-tiep/tottenham-hotspur-vs-milton-keynes-dons-22-07-2026-2200?blv=612098",
            "blv": "BEN 10",
            "blv_id": "612098",
            "status": "success",
            "attempts": 1,
            "attempts_total": 1,
            "ever_attempted": true,
            "valid_stream_ever_found": true,
            "needs_token_refresh": false,
            "completion_reason": "valid_stream",
            "rate_limit_hits": 0,
            "last_http_status": 200,
            "last_stream_count": 1,
            "last_error": "console/error: Failed to load resource: net::ERR_FAILED; console/error: Failed to load resource: net::ERR_FAILED; console/error: Failed to load resource: net::ERR_FAILED"
          },
          "598119": {
            "key": "598119",
            "url": "https://socolivep.cv/truc-tiep/tottenham-hotspur-vs-milton-keynes-dons-22-07-2026-2200?blv=598119",
            "blv": "A TINH",
            "blv_id": "598119",
            "status": "retry",
            "attempts": 1,
            "attempts_total": 1,
            "ever_attempted": true,
            "valid_stream_ever_found": false,
            "needs_token_refresh": true,
            "completion_reason": "",
            "rate_limit_hits": 0,
            "last_http_status": 200,
            "last_stream_count": 0,
            "last_error": "Token cũ đã hết hạn; giữ nguyên attempts_total và trạng thái hoàn tất của BLV."
          },
          "552832": {
            "key": "552832",
            "url": "https://socolivep.cv/truc-tiep/tottenham-hotspur-vs-milton-keynes-dons-22-07-2026-2200?blv=552832",
            "blv": "LOGAN",
            "blv_id": "552832",
            "status": "success",
            "attempts": 1,
            "attempts_total": 1,
            "ever_attempted": true,
            "valid_stream_ever_found": true,
            "needs_token_refresh": false,
            "completion_reason": "valid_stream",
            "rate_limit_hits": 0,
            "last_http_status": 200,
            "last_stream_count": 1,
            "last_error": "console/error: Failed to load resource: net::ERR_FAILED; console/error: Failed to load resource: net::ERR_FAILED; console/error: Failed to load resource: net::ERR_FAILED"
          },
          "__base__": {
            "key": "__base__",
            "url": "https://socolivep.cv/truc-tiep/tottenham-hotspur-vs-milton-keynes-dons-22-07-2026-2200",
            "blv": "XEM NGAY",
            "blv_id": "",
            "status": "pending",
            "attempts": 0,
            "attempts_total": 0,
            "ever_attempted": false,
            "valid_stream_ever_found": false,
            "needs_token_refresh": false,
            "completion_reason": "",
            "rate_limit_hits": 0,
            "last_http_status": null,
            "last_stream_count": 0,
            "last_error": ""
          }
        }
      },
      "attempted_room_ids": [
        "168740",
        "459401",
        "552832",
        "557845",
        "598119",
        "612098"
      ],
      "room_progress": {
        "168740": {
          "key": "168740",
          "url": "https://socolivep.cv/truc-tiep/tottenham-hotspur-vs-milton-keynes-dons-22-07-2026-2200?blv=168740",
          "blv": "ZIDANE",
          "blv_id": "168740",
          "status": "retry",
          "attempts": 1,
          "attempts_total": 1,
          "ever_attempted": true,
          "valid_stream_ever_found": false,
          "needs_token_refresh": true,
          "completion_reason": "",
          "rate_limit_hits": 0,
          "last_http_status": 200,
          "last_stream_count": 0,
          "last_error": "Token cũ đã hết hạn; giữ nguyên attempts_total và trạng thái hoàn tất của BLV."
        },
        "557845": {
          "key": "557845",
          "url": "https://socolivep.cv/truc-tiep/tottenham-hotspur-vs-milton-keynes-dons-22-07-2026-2200?blv=557845",
          "blv": "A TÚ",
          "blv_id": "557845",
          "status": "success",
          "attempts": 1,
          "attempts_total": 1,
          "ever_attempted": true,
          "valid_stream_ever_found": true,
          "needs_token_refresh": false,
          "completion_reason": "valid_stream",
          "rate_limit_hits": 0,
          "last_http_status": 200,
          "last_stream_count": 1,
          "last_error": "console/error: Failed to load resource: net::ERR_FAILED; console/error: Failed to load resource: net::ERR_FAILED; console/error: Failed to load resource: net::ERR_FAILED"
        },
        "459401": {
          "key": "459401",
          "url": "https://socolivep.cv/truc-tiep/tottenham-hotspur-vs-milton-keynes-dons-22-07-2026-2200?blv=459401",
          "blv": "BÉO",
          "blv_id": "459401",
          "status": "success",
          "attempts": 1,
          "attempts_total": 1,
          "ever_attempted": true,
          "valid_stream_ever_found": true,
          "needs_token_refresh": false,
          "completion_reason": "valid_stream",
          "rate_limit_hits": 0,
          "last_http_status": 200,
          "last_stream_count": 1,
          "last_error": "console/error: Failed to load resource: net::ERR_FAILED; console/error: Failed to load resource: net::ERR_FAILED; console/error: Failed to load resource: net::ERR_FAILED"
        },
        "612098": {
          "key": "612098",
          "url": "https://socolivep.cv/truc-tiep/tottenham-hotspur-vs-milton-keynes-dons-22-07-2026-2200?blv=612098",
          "blv": "BEN 10",
          "blv_id": "612098",
          "status": "success",
          "attempts": 1,
          "attempts_total": 1,
          "ever_attempted": true,
          "valid_stream_ever_found": true,
          "needs_token_refresh": false,
          "completion_reason": "valid_stream",
          "rate_limit_hits": 0,
          "last_http_status": 200,
          "last_stream_count": 1,
          "last_error": "console/error: Failed to load resource: net::ERR_FAILED; console/error: Failed to load resource: net::ERR_FAILED; console/error: Failed to load resource: net::ERR_FAILED"
        },
        "598119": {
          "key": "598119",
          "url": "https://socolivep.cv/truc-tiep/tottenham-hotspur-vs-milton-keynes-dons-22-07-2026-2200?blv=598119",
          "blv": "A TINH",
          "blv_id": "598119",
          "status": "retry",
          "attempts": 1,
          "attempts_total": 1,
          "ever_attempted": true,
          "valid_stream_ever_found": false,
          "needs_token_refresh": true,
          "completion_reason": "",
          "rate_limit_hits": 0,
          "last_http_status": 200,
          "last_stream_count": 0,
          "last_error": "Token cũ đã hết hạn; giữ nguyên attempts_total và trạng thái hoàn tất của BLV."
        },
        "552832": {
          "key": "552832",
          "url": "https://socolivep.cv/truc-tiep/tottenham-hotspur-vs-milton-keynes-dons-22-07-2026-2200?blv=552832",
          "blv": "LOGAN",
          "blv_id": "552832",
          "status": "success",
          "attempts": 1,
          "attempts_total": 1,
          "ever_attempted": true,
          "valid_stream_ever_found": true,
          "needs_token_refresh": false,
          "completion_reason": "valid_stream",
          "rate_limit_hits": 0,
          "last_http_status": 200,
          "last_stream_count": 1,
          "last_error": "console/error: Failed to load resource: net::ERR_FAILED; console/error: Failed to load resource: net::ERR_FAILED; console/error: Failed to load resource: net::ERR_FAILED"
        },
        "__base__": {
          "key": "__base__",
          "url": "https://socolivep.cv/truc-tiep/tottenham-hotspur-vs-milton-keynes-dons-22-07-2026-2200",
          "blv": "XEM NGAY",
          "blv_id": "",
          "status": "pending",
          "attempts": 0,
          "attempts_total": 0,
          "ever_attempted": false,
          "valid_stream_ever_found": false,
          "needs_token_refresh": false,
          "completion_reason": "",
          "rate_limit_hits": 0,
          "last_http_status": null,
          "last_stream_count": 0,
          "last_error": ""
        }
      },
      "pending_room_keys": [
        "168740",
        "598119"
      ]
    }
  ]
}